[
    {
        "id":33,
        "tipo":"1",
        "url":"https://www.lajuana.cl/armarios-y-carpas-de-cultivo/?id_category=12&n=37",
        "esquema":{
            "listaProductos":{
                "bloque":{
                    "elemento":"ul",
                    "atributo":"class",
                    "valor":"product_list grid row"
                },
                "secciones":{
                    "elemento":"li",
                    "atributo":"",
                    "valor":""
                },
                "enlaces":{
                    "elemento":"a",
                    "atributo":"class",
                    "valor":"product_img_link",
                    "link":"href"
                }
            },
            "detalleProductos":{
                "bloque":{
                    "elemento":"div",
                    "id":"center_column",
                    "clase":""
                }
            }
        }
    },
    {
        "id":33,
        "tipo":"1",
        "url":"https://www.lajuana.cl/cigarros-electronicos/?id_category=278&n=61",
        "esquema":{
            "listaProductos":{
                "bloque":{
                    "elemento":"ul",
                    "atributo":"class",
                    "valor":"product_list grid row"
                },
                "secciones":{
                    "elemento":"li",
                    "atributo":"",
                    "valor":""
                },
                "enlaces":{
                    "elemento":"a",
                    "atributo":"class",
                    "valor":"product_img_link",
                    "link":"href"
                }
            },
            "detalleProductos":{
                "bloque":{
                    "elemento":"div",
                    "id":"center_column",
                    "clase":""
                }
            }
        }
    },
    {
        "id":33,
        "tipo":"1",
        "url":"https://www.lajuana.cl/cosmeticos-cannabicos/?id_category=303&n=19",
        "esquema":{
            "listaProductos":{
                "bloque":{
                    "elemento":"ul",
                    "atributo":"class",
                    "valor":"product_list grid row"
                },
                "secciones":{
                    "elemento":"li",
                    "atributo":"",
                    "valor":""
                },
                "enlaces":{
                    "elemento":"a",
                    "atributo":"class",
                    "valor":"product_img_link",
                    "link":"href"
                }
            },
            "detalleProductos":{
                "bloque":{
                    "elemento":"div",
                    "id":"center_column",
                    "clase":""
                }
            }
        }
    },
    {
        "id":33,
        "tipo":"1",
        "url":"https://www.lajuana.cl/fertilizantes-y-abonos/?id_category=21&n=204",
        "esquema":{
            "listaProductos":{
                "bloque":{
                    "elemento":"ul",
                    "atributo":"class",
                    "valor":"product_list grid row"
                },
                "secciones":{
                    "elemento":"li",
                    "atributo":"",
                    "valor":""
                },
                "enlaces":{
                    "elemento":"a",
                    "atributo":"class",
                    "valor":"product_img_link",
                    "link":"href"
                }
            },
            "detalleProductos":{
                "bloque":{
                    "elemento":"div",
                    "id":"center_column",
                    "clase":""
                }
            }
        }
    },
    {
        "id":2,
        "tipo":"1",
        "url":"https://tienda-taboo.cl/tienda/9-semillas-de-coleccion?id_category=9&n=54",
        "esquema":{
            "listaProductos":{
                "bloque":{
                    "elemento":"ul",
                    "atributo":"class",
                    "valor":"product_list grid row"
                },
                "secciones":{
                    "elemento":"li",
                    "atributo":"",
                    "valor":""
                },
                "enlaces":{
                    "elemento":"a",
                    "atributo":"class",
                    "valor":"product_img_link",
                    "link":"href"
                }
            },
            "detalleProductos":{
                "bloque":{
                    "elemento":"div",
                    "id":"center_column",
                    "clase":""
                }
            }
        }
    }
]